{
  "id": "bunpou-4",
  "category": "bunpou",
  "paperNumber": 4,
  "name": "Bunpou Paper 4",
  "source_file": "KnowledgeBank/bunpou_questions_n4.md",
  "source_question_range": "Q46-Q60",
  "questionCount": 15,
  "questions": [
    {
      "type": "mcq",
      "stem_html": "「as many as」(n4-046) を あらわす ぶんぽうは どれですか。",
      "choices": [
        "でも",
        "から",
        "も",
        "ばかり"
      ],
      "correctIndex": 2,
      "rationale": "",
      "kbSourceId": "Q46",
      "id": "bunpou-4.1"
    },
    {
      "type": "mcq",
      "stem_html": "「don't ~ (order somebody to not do something)」(n4-047) を あらわす ぶんぽうは どれですか。",
      "choices": [
        "な",
        "ひつようがある",
        "ではないか",
        "かもしれない"
      ],
      "correctIndex": 0,
      "rationale": "",
      "kbSourceId": "Q47",
      "id": "bunpou-4.2"
    },
    {
      "type": "mcq",
      "stem_html": "「such as」(n4-048) を あらわす ぶんぽうは どれですか。",
      "choices": [
        "でも",
        "ばかり",
        "と",
        "など"
      ],
      "correctIndex": 3,
      "rationale": "",
      "kbSourceId": "Q48",
      "id": "bunpou-4.3"
    },
    {
      "type": "mcq",
      "stem_html": "「while」(n4-049) を あらわす ぶんぽうは どれですか。",
      "choices": [
        "がする",
        "あまり〜ない",
        "じゃないか",
        "ながら"
      ],
      "correctIndex": 3,
      "rationale": "",
      "kbSourceId": "Q49",
      "id": "bunpou-4.4"
    },
    {
      "type": "mcq",
      "stem_html": "「not easy to」(n4-050) を あらわす ぶんぽうは どれですか。",
      "choices": [
        "ばあいは",
        "なかなか〜ない",
        "かどうか",
        "間に（あいだに）"
      ],
      "correctIndex": 1,
      "rationale": "",
      "kbSourceId": "Q50",
      "id": "bunpou-4.5"
    },
    {
      "type": "mcq",
      "stem_html": "「must do something」(n4-051) を あらわす ぶんぽうは どれですか。",
      "choices": [
        "かい",
        "なければいけない",
        "ではないか",
        "かもしれない"
      ],
      "correctIndex": 1,
      "rationale": "",
      "kbSourceId": "Q51",
      "id": "bunpou-4.6"
    },
    {
      "type": "mcq",
      "stem_html": "「must do something」(n4-052) を あらわす ぶんぽうは どれですか。",
      "choices": [
        "なければならない",
        "いたします",
        "はずだ",
        "間（あいだ）"
      ],
      "correctIndex": 0,
      "rationale": "",
      "kbSourceId": "Q52",
      "id": "bunpou-4.7"
    },
    {
      "type": "mcq",
      "stem_html": "「if」(n4-053) を あらわす ぶんぽうは どれですか。",
      "choices": [
        "なら",
        "あまり〜ない",
        "ひつようがある",
        "はずがない"
      ],
      "correctIndex": 0,
      "rationale": "",
      "kbSourceId": "Q53",
      "id": "bunpou-4.8"
    },
    {
      "type": "mcq",
      "stem_html": "「do this (soft/firm command)」(n4-054) を あらわす ぶんぽうは どれですか。",
      "choices": [
        "ではないか",
        "いらっしゃる",
        "いたします",
        "なさい"
      ],
      "correctIndex": 3,
      "rationale": "",
      "kbSourceId": "Q54",
      "id": "bunpou-4.9"
    },
    {
      "type": "mcq",
      "stem_html": "「to do (honorific)」(n4-055) を あらわす ぶんぽうは どれですか。",
      "choices": [
        "かもしれない",
        "いたします",
        "かしら",
        "なさる"
      ],
      "correctIndex": 3,
      "rationale": "",
      "kbSourceId": "Q55",
      "id": "bunpou-4.10"
    },
    {
      "type": "mcq",
      "stem_html": "「to notice」(n4-056) を あらわす ぶんぽうは どれですか。",
      "choices": [
        "後で（あとで）",
        "に気がつく（にきがつく）",
        "はずがない",
        "はずだ"
      ],
      "correctIndex": 1,
      "rationale": "",
      "kbSourceId": "Q56",
      "id": "bunpou-4.11"
    },
    {
      "type": "mcq",
      "stem_html": "「to look」(n4-057) を あらわす ぶんぽうは どれですか。",
      "choices": [
        "かしら",
        "に見える（にみえる）",
        "かい",
        "から作る"
      ],
      "correctIndex": 1,
      "rationale": "",
      "kbSourceId": "Q57",
      "id": "bunpou-4.12"
    },
    {
      "type": "mcq",
      "stem_html": "「to make something」(n4-058) を あらわす ぶんぽうは どれですか。",
      "choices": [
        "にする",
        "間（あいだ）",
        "ではないか",
        "Format: `PATTERN"
      ],
      "correctIndex": 0,
      "rationale": "",
      "kbSourceId": "Q58",
      "id": "bunpou-4.13"
    },
    {
      "type": "mcq",
      "stem_html": "「difficult to do」(n4-059) を あらわす ぶんぽうは どれですか。",
      "choices": [
        "間に（あいだに）",
        "にくい",
        "ではないか",
        "かしら"
      ],
      "correctIndex": 1,
      "rationale": "",
      "kbSourceId": "Q59",
      "id": "bunpou-4.14"
    },
    {
      "type": "mcq",
      "stem_html": "「in」(n4-060) を あらわす ぶんぽうは どれですか。",
      "choices": [
        "じゃないか",
        "ばあいは",
        "の中で（のなかで）",
        "だけで"
      ],
      "correctIndex": 2,
      "rationale": "",
      "kbSourceId": "Q60",
      "id": "bunpou-4.15"
    }
  ]
}