{
  "id": "bunpou-3",
  "category": "bunpou",
  "paperNumber": 3,
  "name": "Bunpou Paper 3",
  "source_file": "KnowledgeBank/bunpou_questions_n4.md",
  "source_question_range": "Q31-Q45",
  "questionCount": 15,
  "questions": [
    {
      "type": "mcq",
      "stem_html": "「around」(n4-031) を あらわす ぶんぽうは どれですか。",
      "choices": [
        "いたします",
        "きっと",
        "ございます",
        "ころ"
      ],
      "correctIndex": 3,
      "rationale": "",
      "kbSourceId": "Q31",
      "id": "bunpou-3.1"
    },
    {
      "type": "mcq",
      "stem_html": "「verb nominalizer」(n4-032) を あらわす ぶんぽうは どれですか。",
      "choices": [
        "がる / がっている",
        "こと",
        "じゃないか",
        "後で（あとで）"
      ],
      "correctIndex": 1,
      "rationale": "",
      "kbSourceId": "Q32",
      "id": "bunpou-3.2"
    },
    {
      "type": "mcq",
      "stem_html": "「there are times when」(n4-033) を あらわす ぶんぽうは どれですか。",
      "choices": [
        "出す（だす）",
        "ことがある",
        "ばあいは",
        "ひつようがある"
      ],
      "correctIndex": 1,
      "rationale": "",
      "kbSourceId": "Q33",
      "id": "bunpou-3.3"
    },
    {
      "type": "mcq",
      "stem_html": "「can」(n4-034) を あらわす ぶんぽうは どれですか。",
      "choices": [
        "ことができる",
        "ば",
        "始める（はじめる）",
        "かしら"
      ],
      "correctIndex": 0,
      "rationale": "",
      "kbSourceId": "Q34",
      "id": "bunpou-3.4"
    },
    {
      "type": "mcq",
      "stem_html": "「it has been decided」(n4-035) を あらわす ぶんぽうは どれですか。",
      "choices": [
        "ございます",
        "はずだ",
        "から作る",
        "ことになる"
      ],
      "correctIndex": 3,
      "rationale": "",
      "kbSourceId": "Q35",
      "id": "bunpou-3.5"
    },
    {
      "type": "mcq",
      "stem_html": "「to decide on」(n4-036) を あらわす ぶんぽうは どれですか。",
      "choices": [
        "はずがない",
        "間（あいだ）",
        "ことにする",
        "いたします"
      ],
      "correctIndex": 2,
      "rationale": "",
      "kbSourceId": "Q36",
      "id": "bunpou-3.6"
    },
    {
      "type": "mcq",
      "stem_html": "「to make something」(n4-037) を あらわす ぶんぽうは どれですか。",
      "choices": [
        "だけで",
        "くする",
        "はずがない",
        "はずだ"
      ],
      "correctIndex": 1,
      "rationale": "",
      "kbSourceId": "Q37",
      "id": "bunpou-3.7"
    },
    {
      "type": "mcq",
      "stem_html": "「quickly」(n4-038) を あらわす ぶんぽうは どれですか。",
      "choices": [
        "いたします",
        "ではないか",
        "かい",
        "急に（きゅうに）"
      ],
      "correctIndex": 3,
      "rationale": "",
      "kbSourceId": "Q38",
      "id": "bunpou-3.8"
    },
    {
      "type": "mcq",
      "stem_html": "「by」(n4-039) を あらわす ぶんぽうは どれですか。",
      "choices": [
        "までに",
        "ばあいは",
        "ございます",
        "でございます"
      ],
      "correctIndex": 0,
      "rationale": "",
      "kbSourceId": "Q39",
      "id": "bunpou-3.9"
    },
    {
      "type": "mcq",
      "stem_html": "「as it is」(n4-040) を あらわす ぶんぽうは どれですか。",
      "choices": [
        "間に（あいだに）",
        "はずだ",
        "始める（はじめる）",
        "まま"
      ],
      "correctIndex": 3,
      "rationale": "",
      "kbSourceId": "Q40",
      "id": "bunpou-3.10"
    },
    {
      "type": "mcq",
      "stem_html": "「both」(n4-041) を あらわす ぶんぽうは どれですか。",
      "choices": [
        "または",
        "がる / がっている",
        "ばあいは",
        "かい"
      ],
      "correctIndex": 0,
      "rationale": "",
      "kbSourceId": "Q41",
      "id": "bunpou-3.11"
    },
    {
      "type": "mcq",
      "stem_html": "「like」(n4-042) を あらわす ぶんぽうは どれですか。",
      "choices": [
        "がする",
        "いらっしゃる",
        "がり",
        "みたいだ"
      ],
      "correctIndex": 3,
      "rationale": "",
      "kbSourceId": "Q42",
      "id": "bunpou-3.12"
    },
    {
      "type": "mcq",
      "stem_html": "「like, similar to」(n4-043) を あらわす ぶんぽうは どれですか。",
      "choices": [
        "ではないか",
        "後で（あとで）",
        "ひつようがある",
        "みたいな"
      ],
      "correctIndex": 3,
      "rationale": "",
      "kbSourceId": "Q43",
      "id": "bunpou-3.13"
    },
    {
      "type": "mcq",
      "stem_html": "「like」(n4-044) を あらわす ぶんぽうは どれですか。",
      "choices": [
        "かどうか",
        "あまり〜ない",
        "みたいに",
        "ひつようがある"
      ],
      "correctIndex": 2,
      "rationale": "",
      "kbSourceId": "Q44",
      "id": "bunpou-3.14"
    },
    {
      "type": "mcq",
      "stem_html": "「as many as」(n4-045) を あらわす ぶんぽうは どれですか。",
      "choices": [
        "でも",
        "より",
        "も",
        "ばかり"
      ],
      "correctIndex": 2,
      "rationale": "",
      "kbSourceId": "Q45",
      "id": "bunpou-3.15"
    }
  ]
}